meds_reader/__init__.py
meds_reader/__init__.pyi
meds_reader/_meds_reader.cpython-310-x86_64-linux-gnu.so
meds_reader/meds_reader_convert.cpython-310-x86_64-linux-gnu.so
meds_reader/meds_reader_filter.cpython-310-x86_64-linux-gnu.so
meds_reader/py.typed
meds_reader/transform.py
meds_reader/transform.pyi
meds_reader-0.1.16.dist-info/METADATA
meds_reader-0.1.16.dist-info/WHEEL
meds_reader-0.1.16.dist-info/entry_points.txt
meds_reader-0.1.16.dist-info/top_level.txt
meds_reader-0.1.16.dist-info/RECORD
meds_reader-0.1.16.dist-info/licenses/LICENSE
