Metadata-Version: 2.4
Name: meds_reader
Version: 0.1.16
Summary: A Pythonic interface for MEDS datasets
License: Apache-2.0
Project-URL: Homepage, https://github.com/som-shahlab/meds_reader
Project-URL: Documentation, https://meds-reader.readthedocs.io/en/latest/
Project-URL: Repository, https://github.com/som-shahlab/meds_reader
Project-URL: Tracker, https://github.com/som-shahlab/meds_reader/issues
Requires-Python: >=3.9
License-File: LICENSE
Requires-Dist: pyarrow>=9
Requires-Dist: meds==0.3.3
Requires-Dist: numpy>=1.16
Requires-Dist: pandas>=2.2
Dynamic: license-file
